colambo/__init__.py
colambo/main.py
colambo-0.1.0.dist-info/WHEEL
colambo-0.1.0.dist-info/METADATA
colambo-0.1.0.dist-info/RECORD
